{"cameraMode":{"drawMode":0,"name":"Shaded","section":"Shading Mode"},"sceneLighting":true,"audioPlay":false,"sceneViewState":{"showFog":true,"showMaterialUpdate":false,"showSkybox":true,"showFlares":true,"showImageEffects":true,"showParticleSystems":true},"in2DMode":false,"pivot":{"x":0.944573700428009,"y":0.4345659017562866,"z":6.111560344696045},"rotation":{"x":-0.0005416905623860657,"y":0.9971398711204529,"z":-0.07523652911186218,"w":-0.007178783882409334},"size":3.0342841148376467,"orthographic":false}